{
  "products": [
    {
      "ID": "1",
      "Shoe_Name": "کفش ورزشی نایک آیرمکس",
      "Shoe_Colors": ["Red", "Black", "White"],
      "Shoe_Sizes": ["37", "38", "39", "40", "41"],
      "Shoe_Features": {
        "Sole_Material": "پارچه مش",
        "Height": "پائین",
        "Closure_Method": "بند شانه‌ای",
        "Customer_Satisfaction_Rating": "88%"
      },
      "Price": 1800000,
      "Inventory": 50,
      "Comments": [
        {
          "Review": "کفش خوبیه ولی کمی گرانه.",
          "Rating": 4,
          "Customer_Name": "مهراد"
        },
        {
          "Review": "راضی هستم، خیلی راحته.",
          "Rating": 4.5,
          "Customer_Name": "نازنین"
        },
        {
          "Review": "رنگ‌های جذابی داره و خوب به پا می‌آید.",
          "Rating": 4.2,
          "Customer_Name": "سامان"
        },
        {
          "Review": "کفش عالیه، دوست دارم!",
          "Rating": 5,
          "Customer_Name": "آیدا"
        }
      ],
      "category": "بسکتبال",
      "time_posted": 1645673370439,
      "number_sold": 251
    },
    {
      "ID": "2",
      "Shoe_Name": "کفش ورزشی آدیداس اولترابوست",
      "Shoe_Colors": ["White", "Black", "Blue"],
      "Shoe_Sizes": ["40", "41", "42", "43", "44"],
      "Shoe_Features": {
        "Sole_Material": "پارچه نخی",
        "Height": "کم",
        "Closure_Method": "بند ولکرو",
        "Customer_Satisfaction_Rating": "90%"
      },
      "Price": 1500000,
      "Comments": [
        {
          "Review": "کفش خیلی راحت و خوش‌پا است.",
          "Rating": 5,
          "Customer_Name": "آرمان"
        },
        {
          "Review": "قیمتش نسبت به کیفیتش بالاست.",
          "Rating": 4,
          "Customer_Name": "سارا"
        },
        {
          "Review": "رنگ‌های زیبا و متنوعی دارد.",
          "Rating": 4.5,
          "Customer_Name": "محمد"
        }
      ],
      "category": "فوتبال",
      "time_posted": 1637690012578,
      "number_sold": 146
    },
    {
      "ID": "3",
      "Shoe_Name": "کفش ورزشی پوما فورملا ایکس",
      "Shoe_Colors": ["Grey", "Blue", "Green"],
      "Shoe_Sizes": ["39", "40", "41", "42", "43"],
      "Shoe_Features": {
        "Sole_Material": "فوم",
        "Height": "متوسط",
        "Closure_Method": "بند شانه‌ای",
        "Customer_Satisfaction_Rating": "92%"
      },
      "Price": 1600000,
      "Comments": [
        {
          "Review": "کفش خیلی راحت و سبکه.",
          "Rating": 4.8,
          "Customer_Name": "النا"
        },
        {
          "Review": "قیمت مناسبی داره و کیفیتش خوبه.",
          "Rating": 4.5,
          "Customer_Name": "مهدی"
        },
        {
          "Review": "رنگ‌های زیبا و شیکی داره.",
          "Rating": 4.7,
          "Customer_Name": "فرزاد"
        },
        {
          "Review": "کفش با دوامیه و خوب به پا می‌آید.",
          "Rating": 4.9,
          "Customer_Name": "سمیرا"
        },
        {
          "Review": "خریدم و راضیم!",
          "Rating": 5,
          "Customer_Name": "سارینا"
        }
      ],
      "category": "کوهنوردی",
      "time_posted": 1605030680858,
      "number_sold": 69
    },
    {
      "ID": "4",
      "Shoe_Name": "کفش ورزشی آسیکس ژل‌کایانو 27",
      "Shoe_Colors": ["Black", "Silver", "Blue"],
      "Shoe_Sizes": ["40", "41", "42", "43", "44"],
      "Shoe_Features": {
        "Sole_Material": "ژل",
        "Height": "متوسط",
        "Closure_Method": "بند ولکرو",
        "Customer_Satisfaction_Rating": "91%"
      },
      "Price": 1700000,
      "Comments": [
        {
          "Review": "کفش خیلی راحت و پشتیبانی از پا رو خوب می‌کنه.",
          "Rating": 4.7,
          "Customer_Name": "رضا"
        },
        {
          "Review": "قیمت مناسبی داره و کیفیتش هم خوبه.",
          "Rating": 4.5,
          "Customer_Name": "پریسا"
        },
        {
          "Review": "رنگ‌های زیبا و جذابی داره.",
          "Rating": 4.6,
          "Customer_Name": "علی"
        },
        {
          "Review": "کفش خوبیه و ارزش خرید داره.",
          "Rating": 4.4,
          "Customer_Name": "زهرا"
        }
      ],
      "category": "کوهنوردی",
      "time_posted": 1647658487368,
      "number_sold": 49
    },
    {
      "ID": "5",
      "Shoe_Name": "کفش ورزشی آدیداس نانو 11",
      "Shoe_Colors": ["Grey", "Red", "Black"],
      "Shoe_Sizes": ["39", "40", "41", "42", "43"],
      "Shoe_Features": {
        "Sole_Material": "پارچه نخی",
        "Height": "کم",
        "Closure_Method": "بند ولکرو",
        "Customer_Satisfaction_Rating": "89%"
      },
      "Price": 1550000,
      "Comments": [
        {
          "Review": "کفش خوبیه و راحته.",
          "Rating": 4.5,
          "Customer_Name": "مریم"
        },
        {
          "Review": "قیمتش مناسبه و کیفیتش هم خوبه.",
          "Rating": 4.2,
          "Customer_Name": "علی"
        }
      ],
      "category": "والیبال",
      "time_posted": 1674399956265,
      "number_sold": 118
    },
    {
      "ID": "6",
      "Shoe_Name": "کفش ورزشی آسیکس ژل‌نیمبوس 23",
      "Shoe_Colors": ["Blue", "Silver", "Black"],
      "Shoe_Sizes": ["40", "41", "42", "43", "44"],
      "Shoe_Features": {
        "Sole_Material": "ژل",
        "Height": "متوسط",
        "Closure_Method": "بند ولکرو",
        "Customer_Satisfaction_Rating": "92%"
      },
      "Price": 1750000,
      "Comments": [
        {
          "Review": "کفش خیلی راحت و پشتیبانی از پا رو خوب می‌کنه.",
          "Rating": 4.7,
          "Customer_Name": "رضا"
        },
        {
          "Review": "قیمت مناسبی داره و کیفیتش هم خوبه.",
          "Rating": 4.5,
          "Customer_Name": "پریسا"
        },
        {
          "Review": "رنگ‌های زیبا و جذابی داره.",
          "Rating": 4.6,
          "Customer_Name": "علی"
        },
        {
          "Review": "کفش خوبیه و ارزش خرید داره.",
          "Rating": 4.4,
          "Customer_Name": "زهرا"
        },
        {
          "Review": "راضی هستم، توصیه می‌کنم.",
          "Rating": 4.8,
          "Customer_Name": "نگین"
        },
        {
          "Review": "کفش عالیه، بهترین انتخاب من!",
          "Rating": 5,
          "Customer_Name": "سجاد"
        }
      ],
      "category": "فوتبال",
      "time_posted": 1652402050622,
      "number_sold": 171
    },
    {
      "ID": "7",
      "Shoe_Name": "کفش ورزشی نیو بالانس رانینگ",
      "Shoe_Colors": ["Black", "Grey", "Blue"],
      "Shoe_Sizes": ["38", "39", "40", "41", "42"],
      "Shoe_Features": {
        "Sole_Material": "فوم",
        "Height": "پائین",
        "Closure_Method": "بند ولکرو",
        "Customer_Satisfaction_Rating": "86%"
      },
      "Price": 1650000,
      "Comments": [
        {
          "Review": "کفش خوبیه و قیمتش مناسبه.",
          "Rating": 4.3,
          "Customer_Name": "میلاد"
        },
        {
          "Review": "رنگ‌های زیبایی داره و به پا می‌آید.",
          "Rating": 4.6,
          "Customer_Name": "آرزو"
        },
        {
          "Review": "کفش خوبیه، من راضی ام.",
          "Rating": 4.2,
          "Customer_Name": "نیکا"
        }
      ],
      "category": "والیبال",
      "time_posted": 1682664824780,
      "number_sold": 240
    },
    {
      "ID": "8",
      "Shoe_Name": "کفش ورزشی آدیداس دورتون 9",
      "Shoe_Colors": ["White", "Black", "Red"],
      "Shoe_Sizes": ["39", "40", "41", "42", "43"],
      "Shoe_Features": {
        "Sole_Material": "پارچه نخی",
        "Height": "کم",
        "Closure_Method": "بند ولکرو",
        "Customer_Satisfaction_Rating": "87%"
      },
      "Price": 1700000,
      "Comments": [
        {
          "Review": "کفش خوبیه و راحته.",
          "Rating": 4.5,
          "Customer_Name": "آرمین"
        },
        {
          "Review": "قیمتش مناسبه و کیفیتش هم خوبه.",
          "Rating": 4.2,
          "Customer_Name": "الیزابت"
        },
        {
          "Review": "رنگ‌های زیبا و جذابی داره.",
          "Rating": 4.6,
          "Customer_Name": "جان"
        },
        {
          "Review": "کفش خوبیه و ارزش خرید داره.",
          "Rating": 4.3,
          "Customer_Name": "لیلا"
        }
      ],
      "category": "کوهنوردی",
      "time_posted": 1678258184466,
      "number_sold": 281
    },
    {
      "ID": "9",
      "Shoe_Name": "کفش ورزشی پوما راپیتو فلو",
      "Shoe_Colors": ["Black", "White", "Red"],
      "Shoe_Sizes": ["38", "39", "40", "41", "42"],
      "Shoe_Features": {
        "Sole_Material": "فوم",
        "Height": "کم",
        "Closure_Method": "بند ولکرو",
        "Customer_Satisfaction_Rating": "89%"
      },
      "Price": 1600000,
      "Comments": [
        {
          "Review": "کفش خوبیه و راحته.",
          "Rating": 4.5,
          "Customer_Name": "سارا"
        },
        {
          "Review": "قیمتش مناسبه و کیفیتش هم خوبه.",
          "Rating": 4.2,
          "Customer_Name": "علی"
        },
        {
          "Review": "رنگ‌های زیبایی داره و به پا می‌آید.",
          "Rating": 4.6,
          "Customer_Name": "نیکا"
        },
        {
          "Review": "کفش خوبیه و ارزش خرید داره.",
          "Rating": 4.3,
          "Customer_Name": "مهراد"
        },
        {
          "Review": "راضی هستم، توصیه می‌کنم.",
          "Rating": 4.8,
          "Customer_Name": "ملیکا"
        }
      ],
      "category": "بسکتبال",
      "time_posted": 1629931399058,
      "number_sold": 278
    },
    {
      "ID": "10",
      "Shoe_Name": "کفش ورزشی نایک ایرفورس 1",
      "Shoe_Colors": ["White", "Black", "Red"],
      "Shoe_Sizes": ["37", "38", "39", "40", "41"],
      "Shoe_Features": {
        "Sole_Material": "پارچه مش",
        "Height": "کم",
        "Closure_Method": "بند ولکرو",
        "Customer_Satisfaction_Rating": "90%"
      },
      "Price": 1700000,
      "Comments": [
        {
          "Review": "کفش خوبیه و راحته.",
          "Rating": 4.5,
          "Customer_Name": "آرمان"
        },
        {
          "Review": "قیمتش مناسبه و کیفیتش هم خوبه.",
          "Rating": 4.2,
          "Customer_Name": "سارا"
        },
        {
          "Review": "رنگ‌های زیبایی داره و به پا می‌آید.",
          "Rating": 4.6,
          "Customer_Name": "محمد"
        },
        {
          "Review": "کفش خوبیه و ارزش خرید داره.",
          "Rating": 4.3,
          "Customer_Name": "نازنین"
        }
      ],
      "category": "بسکتبال",
      "time_posted": 1665012766736,
      "number_sold": 185
    },
    {
      "ID": "11",
      "Shoe_Name": "کفش ورزشی آدیداس زون اروپا",
      "Shoe_Colors": ["Black", "Blue", "Grey"],
      "Shoe_Sizes": ["38", "39", "40", "41", "42"],
      "Shoe_Features": {
        "Sole_Material": "پارچه نخی",
        "Height": "کم",
        "Closure_Method": "بند ولکرو",
        "Customer_Satisfaction_Rating": "91%"
      },
      "Price": 1650000,
      "Comments": [
        {
          "Review": "کفش خوبیه و راحته.",
          "Rating": 4.5,
          "Customer_Name": "سام"
        },
        {
          "Review": "قیمتش مناسبه و کیفیتش هم خوبه.",
          "Rating": 4.2,
          "Customer_Name": "ملیکا"
        },
        {
          "Review": "رنگ‌های زیبایی داره و به پا می‌آید.",
          "Rating": 4.6,
          "Customer_Name": "آرش"
        },
        {
          "Review": "کفش خوبیه و ارزش خرید داره.",
          "Rating": 4.3,
          "Customer_Name": "نگین"
        },
        {
          "Review": "راضی هستم، توصیه می‌کنم.",
          "Rating": 4.8,
          "Customer_Name": "آیدا"
        }
      ],
      "category": "کوهنوردی",
      "time_posted": 1643116402043,
      "number_sold": 141
    },
    {
      "ID": "12",
      "Shoe_Name": "کفش ورزشی نایک رن آوالنچ",
      "Shoe_Colors": ["White", "Black", "Red"],
      "Shoe_Sizes": ["38", "39", "40", "41", "42"],
      "Shoe_Features": {
        "Sole_Material": "پارچه مش",
        "Height": "کم",
        "Closure_Method": "بند ولکرو",
        "Customer_Satisfaction_Rating": "88%"
      },
      "Price": 1750000,
      "Comments": [
        {
          "Review": "کفش خوبیه و راحته.",
          "Rating": 4.5,
          "Customer_Name": "آرمان"
        },
        {
          "Review": "قیمتش مناسبه و کیفیتش هم خوبه.",
          "Rating": 4.2,
          "Customer_Name": "سارا"
        },
        {
          "Review": "رنگ‌های زیبایی داره و به پا می‌آید.",
          "Rating": 4.6,
          "Customer_Name": "محمد"
        }
      ],
      "category": "دومیدانی",
      "time_posted": 1692775531996,
      "number_sold": 24
    },
    {
      "ID": "13",
      "Shoe_Name": "کفش ورزشی آدیداس زون ایکس",
      "Shoe_Colors": ["Black", "Grey", "Red"],
      "Shoe_Sizes": ["38", "39", "40", "41", "42"],
      "Shoe_Features": {
        "Sole_Material": "پارچه نخی",
        "Height": "کم",
        "Closure_Method": "بند ولکرو",
        "Customer_Satisfaction_Rating": "90%"
      },
      "Price": 1600000,
      "Comments": [
        {
          "Review": "کفش خوبیه و راحته.",
          "Rating": 4.5,
          "Customer_Name": "سارا"
        },
        {
          "Review": "قیمتش مناسبه و کیفیتش هم خوبه.",
          "Rating": 4.2,
          "Customer_Name": "علی"
        },
        {
          "Review": "رنگ‌های زیبایی داره و به پا می‌آید.",
          "Rating": 4.6,
          "Customer_Name": "نیکا"
        },
        {
          "Review": "کفش خوبیه و ارزش خرید داره.",
          "Rating": 4.3,
          "Customer_Name": "مهراد"
        },
        {
          "Review": "راضی هستم، توصیه می‌کنم.",
          "Rating": 4.8,
          "Customer_Name": "ملیکا"
        },
        {
          "Review": "کفش عالیه، بهترین انتخاب من!",
          "Rating": 5,
          "Customer_Name": "سجاد"
        }
      ],
      "category": "بسکتبال",
      "time_posted": 1638606110990,
      "number_sold": 286
    },
    {
      "ID": "14",
      "Shoe_Name": "کفش ورزشی پوما نیترو",
      "Shoe_Colors": ["Black", "White", "Blue"],
      "Shoe_Sizes": ["38", "39", "40", "41", "42"],
      "Shoe_Features": {
        "Sole_Material": "پارچه مش",
        "Height": "کم",
        "Closure_Method": "بند ولکرو",
        "Customer_Satisfaction_Rating": "88%"
      },
      "Price": 1500000,
      "Comments": [
        {
          "Review": "کفش خوبیه و راحته.",
          "Rating": 4.5,
          "Customer_Name": "آرمان"
        },
        {
          "Review": "قیمتش مناسبه و کیفیتش هم خوبه.",
          "Rating": 4.2,
          "Customer_Name": "سارا"
        },
        {
          "Review": "رنگ‌های زیبایی داره و به پا می‌آید.",
          "Rating": 4.6,
          "Customer_Name": "محمد"
        }
      ],
      "category": "بسکتبال",
      "time_posted": 1643806762275,
      "number_sold": 174
    },
    {
      "ID": "15",
      "Shoe_Name": "کفش ورزشی نایک ایرمکس 97",
      "Shoe_Colors": ["White", "Silver", "Red"],
      "Shoe_Sizes": ["38", "39", "40", "41", "42"],
      "Shoe_Features": {
        "Sole_Material": "پارچه مش",
        "Height": "متوسط",
        "Closure_Method": "بند ولکرو",
        "Customer_Satisfaction_Rating": "89%"
      },
      "Price": 1700000,
      "Comments": [
        {
          "Review": "کفش خوبیه و راحته.",
          "Rating": 4.5,
          "Customer_Name": "مهدی"
        },
        {
          "Review": "قیمتش مناسبه و کیفیتش هم خوبه.",
          "Rating": 4.2,
          "Customer_Name": "فاطمه"
        },
        {
          "Review": "رنگ‌های زیبایی داره و به پا می‌آید.",
          "Rating": 4.6,
          "Customer_Name": "علی"
        },
        {
          "Review": "کفش خوبیه و ارزش خرید داره.",
          "Rating": 4.3,
          "Customer_Name": "زهرا"
        }
      ],
      "category": "فوتبال",
      "time_posted": 1673841431064,
      "number_sold": 194
    },
    {
      "ID": "16",
      "Shoe_Name": "کفش ورزشی نایک ایرمکس 270",
      "Shoe_Colors": ["Black", "White", "Orange"],
      "Shoe_Sizes": ["38", "39", "40", "41", "42"],
      "Shoe_Features": {
        "Sole_Material": "پارچه مش",
        "Height": "متوسط",
        "Closure_Method": "بند ولکرو",
        "Customer_Satisfaction_Rating": "91%"
      },
      "Price": 1800000,
      "Comments": [
        {
          "Review": "کفش خوبیه و راحته.",
          "Rating": 4.5,
          "Customer_Name": "نیما"
        },
        {
          "Review": "قیمتش مناسبه و کیفیتش هم خوبه.",
          "Rating": 4.2,
          "Customer_Name": "لیلا"
        },
        {
          "Review": "رنگ‌های زیبایی داره و به پا می‌آید.",
          "Rating": 4.6,
          "Customer_Name": "علی"
        },
        {
          "Review": "کفش خوبیه و ارزش خرید داره.",
          "Rating": 4.3,
          "Customer_Name": "فرزاد"
        },
        {
          "Review": "راضی هستم، توصیه می‌کنم.",
          "Rating": 4.8,
          "Customer_Name": "الهام"
        }
      ],
      "category": "والیبال",
      "time_posted": 1690881192431,
      "number_sold": 82
    },
    {
      "ID": "17",
      "Shoe_Name": "کفش ورزشی آدیداس الفا بانس",
      "Shoe_Colors": ["Black", "Grey", "Blue"],
      "Shoe_Sizes": ["38", "39", "40", "41", "42"],
      "Shoe_Features": {
        "Sole_Material": "پارچه نخی",
        "Height": "کم",
        "Closure_Method": "بند ولکرو",
        "Customer_Satisfaction_Rating": "87%"
      },
      "Price": 1600000,
      "Comments": [
        {
          "Review": "کفش خوبیه و راحته.",
          "Rating": 4.5,
          "Customer_Name": "آرمان"
        },
        {
          "Review": "قیمتش مناسبه و کیفیتش هم خوبه.",
          "Rating": 4.2,
          "Customer_Name": "سارا"
        },
        {
          "Review": "رنگ‌های زیبایی داره و به پا می‌آید.",
          "Rating": 4.6,
          "Customer_Name": "محمد"
        }
      ],
      "category": "فوتبال",
      "time_posted": 1619738705786,
      "number_sold": 20
    },
    {
      "ID": "18",
      "Shoe_Name": "کفش ورزشی نایک ایرمکس 270",
      "Shoe_Colors": ["Black", "White", "Orange"],
      "Shoe_Sizes": ["38", "39", "40", "41", "42"],
      "Shoe_Features": {
        "Sole_Material": "پارچه مش",
        "Height": "متوسط",
        "Closure_Method": "بند ولکرو",
        "Customer_Satisfaction_Rating": "91%"
      },
      "Price": 1800000,
      "Comments": [
        {
          "Review": "کفش خوبیه و راحته.",
          "Rating": 4.5,
          "Customer_Name": "نیما"
        },
        {
          "Review": "قیمتش مناسبه و کیفیتش هم خوبه.",
          "Rating": 4.2,
          "Customer_Name": "لیلا"
        },
        {
          "Review": "رنگ‌های زیبایی داره و به پا می‌آید.",
          "Rating": 4.6,
          "Customer_Name": "علی"
        },
        {
          "Review": "کفش خوبیه و ارزش خرید داره.",
          "Rating": 4.3,
          "Customer_Name": "فرزاد"
        },
        {
          "Review": "راضی هستم، توصیه می‌کنم.",
          "Rating": 4.8,
          "Customer_Name": "الهام"
        }
      ],
      "category": "دومیدانی",
      "time_posted": 1634748604689,
      "number_sold": 65
    },
    {
      "ID": "19",
      "Shoe_Name": "کفش ورزشی آدیداس الفا بانس",
      "Shoe_Colors": ["Black", "Grey", "Blue"],
      "Shoe_Sizes": ["38", "39", "40", "41", "42"],
      "Shoe_Features": {
        "Sole_Material": "پارچه نخی",
        "Height": "کم",
        "Closure_Method": "بند ولکرو",
        "Customer_Satisfaction_Rating": "87%"
      },
      "Price": 1600000,
      "Comments": [
        {
          "Review": "کفش خوبیه و راحته.",
          "Rating": 4.5,
          "Customer_Name": "آرمان"
        },
        {
          "Review": "قیمتش مناسبه و کیفیتش هم خوبه.",
          "Rating": 4.2,
          "Customer_Name": "سارا"
        },
        {
          "Review": "رنگ‌های زیبایی داره و به پا می‌آید.",
          "Rating": 4.6,
          "Customer_Name": "محمد"
        }
      ],
      "category": "کوهنوردی",
      "time_posted": 1677652450452,
      "number_sold": 59
    },
    {
      "ID": "20",
      "Shoe_Name": "کفش ورزشی نایک جوردن 1",
      "Shoe_Colors": ["Black", "Red", "White"],
      "Shoe_Sizes": ["38", "39", "40", "41", "42"],
      "Shoe_Features": {
        "Sole_Material": "پارچه مش",
        "Height": "کم",
        "Closure_Method": "بند ولکرو",
        "Customer_Satisfaction_Rating": "92%"
      },
      "Price": 1750000,
      "Comments": [
        {
          "Review": "کفش خوبیه و راحته.",
          "Rating": 4.5,
          "Customer_Name": "رضا"
        },
        {
          "Review": "قیمتش مناسبه و کیفیتش هم خوبه.",
          "Rating": 4.2,
          "Customer_Name": "پریسا"
        },
        {
          "Review": "رنگ‌های زیبایی داره و به پا می‌آید.",
          "Rating": 4.6,
          "Customer_Name": "سعید"
        },
        {
          "Review": "کفش خوبیه و ارزش خرید داره.",
          "Rating": 4.3,
          "Customer_Name": "نیکا"
        },
        {
          "Review": "راضی هستم، توصیه می‌کنم.",
          "Rating": 4.8,
          "Customer_Name": "آیدا"
        },
        {
          "Review": "خیلی عالیه، بهترین کفشی که داشتم.",
          "Rating": 5,
          "Customer_Name": "مهدی"
        }
      ],
      "category": "دومیدانی",
      "time_posted": 1649341255634,
      "number_sold": 248
    },
    {
      "ID": "21",
      "Shoe_Name": "کفش ورزشی نایک جوانانه",
      "Shoe_Colors": ["Red", "Black", "Grey"],
      "Shoe_Sizes": ["35", "36", "37", "38", "39"],
      "Shoe_Features": {
        "Sole_Material": "پارچه نخی",
        "Height": "کم",
        "Closure_Method": "بند ولکرو",
        "Customer_Satisfaction_Rating": "85%"
      },
      "Price": 1500000,
      "Comments": [
        {
          "Review": "کفش خوبیه و راحته.",
          "Rating": 4.5,
          "Customer_Name": "آرمان"
        },
        {
          "Review": "قیمتش مناسبه و کیفیتش هم خوبه.",
          "Rating": 4.2,
          "Customer_Name": "سارا"
        },
        {
          "Review": "رنگ‌های زیبایی داره و به پا می‌آید.",
          "Rating": 4.6,
          "Customer_Name": "محمد"
        }
      ],
      "category": "کوهنوردی",
      "time_posted": 1664864028796,
      "number_sold": 234
    },
    {
      "ID": "22",
      "Shoe_Name": "کفش ورزشی آدیداس سوپراستار",
      "Shoe_Colors": ["White", "Black", "Gold"],
      "Shoe_Sizes": ["38", "39", "40", "41", "42"],
      "Shoe_Features": {
        "Sole_Material": "پارچه مش",
        "Height": "کم",
        "Closure_Method": "بند ولکرو",
        "Customer_Satisfaction_Rating": "88%"
      },
      "Price": 1700000,
      "Comments": [
        {
          "Review": "کفش خوبیه و راحته.",
          "Rating": 4.5,
          "Customer_Name": "آرمان"
        },
        {
          "Review": "قیمتش مناسبه و کیفیتش هم خوبه.",
          "Rating": 4.2,
          "Customer_Name": "سارا"
        },
        {
          "Review": "رنگ‌های زیبایی داره و به پا می‌آید.",
          "Rating": 4.6,
          "Customer_Name": "محمد"
        },
        {
          "Review": "کفش خوبیه و ارزش خرید داره.",
          "Rating": 4.3,
          "Customer_Name": "علی"
        }
      ],
      "category": "فوتبال",
      "time_posted": 1684176508026,
      "number_sold": 166
    },
    {
      "ID": "23",
      "Shoe_Name": "کفش ورزشی پوما فیلا",
      "Shoe_Colors": ["Blue", "Red", "Grey"],
      "Shoe_Sizes": ["38", "39", "40", "41", "42"],
      "Shoe_Features": {
        "Sole_Material": "پارچه مش",
        "Height": "کم",
        "Closure_Method": "بند ولکرو",
        "Customer_Satisfaction_Rating": "89%"
      },
      "Price": 1750000,
      "Comments": [
        {
          "Review": "کفش خوبیه و راحته.",
          "Rating": 4.5,
          "Customer_Name": "نیما"
        },
        {
          "Review": "قیمتش مناسبه و کیفیتش هم خوبه.",
          "Rating": 4.2,
          "Customer_Name": "لیلا"
        },
        {
          "Review": "رنگ‌های زیبایی داره و به پا می‌آید.",
          "Rating": 4.6,
          "Customer_Name": "علی"
        },
        {
          "Review": "کفش خوبیه و ارزش خرید داره.",
          "Rating": 4.3,
          "Customer_Name": "فرزاد"
        },
        {
          "Review": "راضی هستم، توصیه می‌کنم.",
          "Rating": 4.8,
          "Customer_Name": "الهام"
        }
      ],
      "category": "بسکتبال",
      "time_posted": 1648506989205,
      "number_sold": 157
    },
    {
      "ID": "24",
      "Shoe_Name": "کفش ورزشی نایک کورتز",
      "Shoe_Colors": ["White", "Black", "Red"],
      "Shoe_Sizes": ["38", "39", "40", "41", "42"],
      "Shoe_Features": {
        "Sole_Material": "پارچه مش",
        "Height": "کم",
        "Closure_Method": "بند ولکرو",
        "Customer_Satisfaction_Rating": "85%"
      },
      "Price": 1600000,
      "Comments": [
        {
          "Review": "کفش خوبیه و راحته.",
          "Rating": 4.5,
          "Customer_Name": "آرمان"
        },
        {
          "Review": "قیمتش مناسبه و کیفیتش هم خوبه.",
          "Rating": 4.2,
          "Customer_Name": "سارا"
        }
      ],
      "category": "بسکتبال",
      "time_posted": 1595839085058,
      "number_sold": 209
    },
    {
      "ID": "25",
      "Shoe_Name": "کفش ورزشی آدیداس دورتموند",
      "Shoe_Colors": ["Black", "Yellow", "White"],
      "Shoe_Sizes": ["38", "39", "40", "41", "42"],
      "Shoe_Features": {
        "Sole_Material": "پارچه نخی",
        "Height": "کم",
        "Closure_Method": "بند ولکرو",
        "Customer_Satisfaction_Rating": "87%"
      },
      "Price": 1700000,
      "Comments": [
        {
          "Review": "کفش خوبیه و راحته.",
          "Rating": 4.5,
          "Customer_Name": "آرمان"
        },
        {
          "Review": "قیمتش مناسبه و کیفیتش هم خوبه.",
          "Rating": 4.2,
          "Customer_Name": "سارا"
        },
        {
          "Review": "رنگ‌های زیبایی داره و به پا می‌آید.",
          "Rating": 4.6,
          "Customer_Name": "محمد"
        }
      ],
      "category": "والیبال",
      "time_posted": 1613593903493,
      "number_sold": 51
    },
    {
      "ID": "26",
      "Shoe_Name": "کفش ورزشی نایک اسپانسر",
      "Shoe_Colors": ["Black", "Red", "White"],
      "Shoe_Sizes": ["38", "39", "40", "41", "42"],
      "Shoe_Features": {
        "Sole_Material": "پارچه مش",
        "Height": "کم",
        "Closure_Method": "بند ولکرو",
        "Customer_Satisfaction_Rating": "90%"
      },
      "Price": 1750000,
      "Comments": [
        {
          "Review": "کفش خوبیه و راحته.",
          "Rating": 4.5,
          "Customer_Name": "نیما"
        },
        {
          "Review": "قیمتش مناسبه و کیفیتش هم خوبه.",
          "Rating": 4.2,
          "Customer_Name": "لیلا"
        },
        {
          "Review": "رنگ‌های زیبایی داره و به پا می‌آید.",
          "Rating": 4.6,
          "Customer_Name": "علی"
        },
        {
          "Review": "کفش خوبیه و ارزش خرید داره.",
          "Rating": 4.3,
          "Customer_Name": "فرزاد"
        },
        {
          "Review": "راضی هستم، توصیه می‌کنم.",
          "Rating": 4.8,
          "Customer_Name": "الهام"
        },
        {
          "Review": "عالیه، دوست دارم.",
          "Rating": 5,
          "Customer_Name": "مهران"
        }
      ],
      "category": "فوتبال",
      "time_posted": 1658249352667,
      "number_sold": 249
    },
    {
      "ID": "27",
      "Shoe_Name": "کفش ورزشی پوما تانیک",
      "Shoe_Colors": ["White", "Blue", "Red"],
      "Shoe_Sizes": ["38", "39", "40", "41", "42"],
      "Shoe_Features": {
        "Sole_Material": "پارچه نخی",
        "Height": "کم",
        "Closure_Method": "بند ولکرو",
        "Customer_Satisfaction_Rating": "88%"
      },
      "Price": 1700000,
      "Comments": [
        {
          "Review": "کفش خوبیه و راحته.",
          "Rating": 4.5,
          "Customer_Name": "آرمان"
        },
        {
          "Review": "قیمتش مناسبه و کیفیتش هم خوبه.",
          "Rating": 4.2,
          "Customer_Name": "سارا"
        },
        {
          "Review": "رنگ‌های زیبایی داره و به پا می‌آید.",
          "Rating": 4.6,
          "Customer_Name": "محمد"
        },
        {
          "Review": "کفش خوبیه و ارزش خرید داره.",
          "Rating": 4.3,
          "Customer_Name": "علی"
        }
      ],
      "category": "فوتبال",
      "time_posted": 1680270998368,
      "number_sold": 293
    },
    {
      "ID": "28",
      "Shoe_Name": "کفش ورزشی آدیداس نانو",
      "Shoe_Colors": ["Black", "Grey", "Blue"],
      "Shoe_Sizes": ["38", "39", "40", "41", "42"],
      "Shoe_Features": {
        "Sole_Material": "پارچه مش",
        "Height": "کم",
        "Closure_Method": "بند ولکرو",
        "Customer_Satisfaction_Rating": "87%"
      },
      "Price": 1600000,
      "Comments": [
        {
          "Review": "کفش خوبیه و راحته.",
          "Rating": 4.5,
          "Customer_Name": "آرمان"
        },
        {
          "Review": "قیمتش مناسبه و کیفیتش هم خوبه.",
          "Rating": 4.2,
          "Customer_Name": "سارا"
        },
        {
          "Review": "رنگ‌های زیبایی داره و به پا می‌آید.",
          "Rating": 4.6,
          "Customer_Name": "محمد"
        }
      ],
      "category": "دومیدانی",
      "time_posted": 1610688827790,
      "number_sold": 111
    },
    {
      "ID": "29",
      "Shoe_Name": "کفش ورزشی نایک پگاسوس",
      "Shoe_Colors": ["Grey", "Black", "Red"],
      "Shoe_Sizes": ["38", "39", "40", "41", "42"],
      "Shoe_Features": {
        "Sole_Material": "پارچه مش",
        "Height": "کم",
        "Closure_Method": "بند ولکرو",
        "Customer_Satisfaction_Rating": "88%"
      },
      "Price": 1700000,
      "Comments": [
        {
          "Review": "کفش خوبیه و راحته.",
          "Rating": 4.5,
          "Customer_Name": "آرمان"
        },
        {
          "Review": "قیمتش مناسبه و کیفیتش هم خوبه.",
          "Rating": 4.2,
          "Customer_Name": "سارا"
        },
        {
          "Review": "رنگ‌های زیبایی داره و به پا می‌آید.",
          "Rating": 4.6,
          "Customer_Name": "محمد"
        }
      ],
      "category": "والیبال",
      "time_posted": 1681909749013,
      "number_sold": 62
    },
    {
      "ID": "30",
      "Shoe_Name": "کفش ورزشی پوما سوپرنوا",
      "Shoe_Colors": ["White", "Black", "Blue"],
      "Shoe_Sizes": ["38", "39", "40", "41", "42"],
      "Shoe_Features": {
        "Sole_Material": "پارچه مش",
        "Height": "کم",
        "Closure_Method": "بند ولکرو",
        "Customer_Satisfaction_Rating": "86%"
      },
      "Price": 1600000,
      "Comments": [
        {
          "Review": "کفش خوبیه و راحته.",
          "Rating": 4.5,
          "Customer_Name": "آرمان"
        },
        {
          "Review": "قیمتش مناسبه و کیفیتش هم خوبه.",
          "Rating": 4.2,
          "Customer_Name": "سارا"
        }
      ],
      "category": "کوهنوردی",
      "time_posted": 1615736389431,
      "number_sold": 107
    },
    {
      "ID": "31",
      "Shoe_Name": "کفش ورزشی نایک رانر",
      "Shoe_Colors": ["Black", "Grey", "White"],
      "Shoe_Sizes": ["38", "39", "40", "41", "42"],
      "Shoe_Features": {
        "Sole_Material": "پارچه مش",
        "Height": "کم",
        "Closure_Method": "بند ولکرو",
        "Customer_Satisfaction_Rating": "85%"
      },
      "Price": 1600000,
      "Comments": [],
      "category": "والیبال",
      "time_posted": 1641270423633,
      "number_sold": 222
    },
    {
      "ID": "32",
      "Shoe_Name": "کفش ورزشی آدیداس کمپوزیت",
      "Shoe_Colors": ["Black", "Grey", "Red"],
      "Shoe_Sizes": ["38", "39", "40", "41", "42"],
      "Shoe_Features": {
        "Sole_Material": "پارچه مش",
        "Height": "کم",
        "Closure_Method": "بند ولکرو",
        "Customer_Satisfaction_Rating": "88%"
      },
      "Price": 1700000,
      "Comments": [],
      "category": "والیبال",
      "time_posted": 1648000935385,
      "number_sold": 33
    },
    {
      "ID": "33",
      "Shoe_Name": "کفش ورزشی نایک اسپرت",
      "Shoe_Colors": ["Black", "Grey", "White"],
      "Shoe_Sizes": ["38", "39", "40", "41", "42"],
      "Shoe_Features": {
        "Sole_Material": "پارچه مش",
        "Height": "کم",
        "Closure_Method": "بند ولکرو",
        "Customer_Satisfaction_Rating": "87%"
      },
      "Price": 1600000,
      "Comments": [],
      "category": "فوتبال",
      "time_posted": 1661817358576,
      "number_sold": 181
    }
  ]
}
